PyProject3/__init__.py
PyProject3/contents.py
PyProject3/create_project.py
PyProject3/project.py
PyProject3/schema.py
PyProject3/utils.py
PyProject3/TemplateProject/__init__.py
PyProject3/TemplateProject/requirements.txt
PyProject3/TemplateProject/TemplateProject/connections/__init__.py
PyProject3/TemplateProject/TemplateProject/connections/mqtt_client.py
PyProject3/TemplateProject/TemplateProject/connections/requirements.txt
PyProject3/TemplateProject/TemplateProject/connections/zmq_message_compress.py
PyProject3/TemplateProject/TemplateProject/connections/zmq_pub_sub.py
PyProject3/TemplateProject/TemplateProject/connections/zmq_push_pull.py
PyProject3/TemplateProject/TemplateProject/connections/zmq_qt.py
PyProject3/TemplateProject/TemplateProject/settings/__init__.py
PyProject3/TemplateProject/TemplateProject/settings/config.yaml
PyProject3/TemplateProject/TemplateProject/settings/constants.py
PyProject3/TemplateProject/TemplateProject/settings/log_config.py
PyProject3/TemplateProject/TemplateProject/settings/logging_utils.py
PyProject3/TemplateProject/TemplateProject/settings/test_settings.py
PyProject3/TemplateProject/TemplateProject/settings/yaml_config.py
PyProject3/TemplateProject/TemplateProject/stores/__init__.py
PyProject3/TemplateProject/TemplateProject/stores/model.py
PyProject3/TemplateProject/TemplateProject/stores/sql_helper.py
PyProject3/TemplateProject/TemplateProject/stores/test_sql_helper.py
PyProject3/TemplateProject/TemplateProject/threads/__init__.py
PyProject3/TemplateProject/TemplateProject/threads/simple_thread.py
PyProject3/TemplateProject/TemplateProject/utils/clock_utils.py
PyProject3/TemplateProject/TemplateProject/utils/contextmenu_utils.py
PyProject3/TemplateProject/TemplateProject/utils/f3d_utils.py
PyProject3/TemplateProject/TemplateProject/utils/gpu_utils.py
PyProject3/TemplateProject/TemplateProject/widgets/QTreeWidget/MyQTreeWidget.py
PyProject3/TemplateProject/TemplateProject/widgets/QTreeWidget/res/3d.png
pyproject3-1.2.9.dist-info/METADATA
pyproject3-1.2.9.dist-info/WHEEL
pyproject3-1.2.9.dist-info/entry_points.txt
pyproject3-1.2.9.dist-info/top_level.txt
pyproject3-1.2.9.dist-info/RECORD
