Metadata-Version: 2.1
Name: pyproject3
Version: 1.2.9
Summary: 一个快速创建Python新项目的轮子
Home-page: https://gitee.com/jiangbin2020/py-project
Author: Peter Jiang
Author-email: 07jiangbin@163.com
